wfgfw/__init__.py
wfgfw/flask_wfgfw.py
wfgfw/wfgfw.py
wfgfw-0.1.8.dist-info/METADATA
wfgfw-0.1.8.dist-info/WHEEL
wfgfw-0.1.8.dist-info/top_level.txt
wfgfw-0.1.8.dist-info/RECORD
