Metadata-Version: 2.1
Name: wfgfw
Version: 0.1.8
Summary: word filter for gfw, include plugin for flask. download keywords: https://github.com/observerss/textfilter
Home-page: https://github.com/dantezhu/wfgfw
Author: dantezhu
Author-email: dantezhu <zny2008@gmail.com>
License: BSD
Project-URL: Homepage, https://github.com/dantezhu/wfgfw
Platform: any
